gitmoji_commits/__init__.py
cz_gitmoji_commits-0.0.0.dist-info/LICENSE
cz_gitmoji_commits-0.0.0.dist-info/METADATA
cz_gitmoji_commits-0.0.0.dist-info/WHEEL
cz_gitmoji_commits-0.0.0.dist-info/top_level.txt
cz_gitmoji_commits-0.0.0.dist-info/RECORD
