Metadata-Version: 2.1
Name: cz-gitmoji-commits
Version: 0.0.0
Summary: 🔖 Commitizen plugin for Gitmoji-based version bumps and changelogs 😜
Author-email: Kamil Paduszyński <paduszyk@gmail.com>
Project-URL: Repository, https://github.com/paduszyk/cz-gitmoji-commits
Keywords: commitizen,gitmoji
Classifier: Development Status :: 1 - Planning
Classifier: Environment :: Console
Classifier: Intended Audience :: Developers
Classifier: License :: OSI Approved :: MIT License
Classifier: Natural Language :: English
Classifier: Operating System :: OS Independent
Classifier: Programming Language :: Python
Classifier: Programming Language :: Python :: 3
Classifier: Programming Language :: Python :: 3.8
Classifier: Programming Language :: Python :: 3.9
Classifier: Programming Language :: Python :: 3.10
Classifier: Programming Language :: Python :: 3.11
Requires-Python: >=3.8
License-File: LICENSE
Requires-Dist: commitizen
Provides-Extra: dev
Requires-Dist: pre-commit ; extra == 'dev'
Requires-Dist: tox ; extra == 'dev'
Provides-Extra: lint
Provides-Extra: test
Requires-Dist: coverage ; extra == 'test'
Requires-Dist: pytest ; extra == 'test'
Requires-Dist: pytest-custom-exit-code ; extra == 'test'
